scrapy_item_ingest/__init__.py
scrapy_item_ingest/config/__init__.py
scrapy_item_ingest/config/settings.py
scrapy_item_ingest/database/__init__.py
scrapy_item_ingest/database/connection.py
scrapy_item_ingest/database/schema.py
scrapy_item_ingest/extensions/__init__.py
scrapy_item_ingest/extensions/base.py
scrapy_item_ingest/extensions/logging.py
scrapy_item_ingest/pipelines/__init__.py
scrapy_item_ingest/pipelines/base.py
scrapy_item_ingest/pipelines/items.py
scrapy_item_ingest/pipelines/main.py
scrapy_item_ingest/pipelines/requests.py
scrapy_item_ingest/utils/__init__.py
scrapy_item_ingest/utils/fingerprint.py
scrapy_item_ingest/utils/serialization.py
scrapy_item_ingest/utils/time.py
scrapy_item_ingest-0.2.7.dist-info/licenses/LICENSE
scrapy_item_ingest-0.2.7.dist-info/METADATA
scrapy_item_ingest-0.2.7.dist-info/WHEEL
scrapy_item_ingest-0.2.7.dist-info/entry_points.txt
scrapy_item_ingest-0.2.7.dist-info/top_level.txt
scrapy_item_ingest-0.2.7.dist-info/RECORD
