Metadata-Version: 2.4
Name: scrapy_item_ingest
Version: 0.2.7
Summary: Scrapy extension for database ingestion with job/spider tracking
Home-page: https://github.com/fawadss1/scrapy_item_ingest
Author: Fawad Ali
Author-email: fawadstar6@gmail.com
Project-URL: Documentation, https://scrapy-item-ingest.readthedocs.io/
Project-URL: Source, https://github.com/fawadss1/scrapy_item_ingest
Project-URL: Tracker, https://github.com/fawadss1/scrapy_item_ingest/issues
Keywords: scrapy,database,postgresql,web-scraping,data-pipeline
Classifier: Development Status :: 4 - Beta
Classifier: Intended Audience :: Developers
Classifier: License :: OSI Approved :: MIT License
Classifier: Operating System :: OS Independent
Classifier: Programming Language :: Python :: 3
Classifier: Programming Language :: Python :: 3.7
Classifier: Programming Language :: Python :: 3.8
Classifier: Programming Language :: Python :: 3.9
Classifier: Programming Language :: Python :: 3.10
Classifier: Programming Language :: Python :: 3.11
Classifier: Framework :: Scrapy
Classifier: Topic :: Software Development :: Libraries :: Python Modules
Classifier: Topic :: Internet :: WWW/HTTP
Classifier: Topic :: Database
Requires-Python: >=3.7
License-File: LICENSE
Requires-Dist: scrapy>=2.13.3
Requires-Dist: psycopg2-binary>=2.9.10
Requires-Dist: itemadapter>=0.11.0
Requires-Dist: SQLAlchemy>=2.0.41
Requires-Dist: pytz>=2025.2
Provides-Extra: docs
Requires-Dist: sphinx>=5.0.0; extra == "docs"
Requires-Dist: sphinx_rtd_theme>=1.2.0; extra == "docs"
Requires-Dist: myst-parser>=0.18.0; extra == "docs"
Requires-Dist: sphinx-autodoc-typehints>=1.19.0; extra == "docs"
Requires-Dist: sphinx-copybutton>=0.5.0; extra == "docs"
Provides-Extra: dev
Requires-Dist: pytest>=7.0.0; extra == "dev"
Requires-Dist: pytest-cov>=4.0.0; extra == "dev"
Requires-Dist: black>=22.0.0; extra == "dev"
Requires-Dist: flake8>=5.0.0; extra == "dev"
Requires-Dist: mypy>=0.991; extra == "dev"
Requires-Dist: pre-commit>=2.20.0; extra == "dev"
Provides-Extra: test
Requires-Dist: pytest>=7.0.0; extra == "test"
Requires-Dist: pytest-cov>=4.0.0; extra == "test"
Requires-Dist: pytest-mock>=3.8.0; extra == "test"
Dynamic: author
Dynamic: author-email
Dynamic: classifier
Dynamic: description
Dynamic: description-content-type
Dynamic: home-page
Dynamic: keywords
Dynamic: license-file
Dynamic: project-url
Dynamic: provides-extra
Dynamic: requires-dist
Dynamic: requires-python
Dynamic: summary
